freesurfer_volume_reader/__init__.py
freesurfer_volume_reader/__main__.py
freesurfer_volume_reader/ashs.py
freesurfer_volume_reader/freesurfer.py
freesurfer_volume_reader/version.py
freesurfer_volume_reader-2.1.1.dist-info/METADATA
freesurfer_volume_reader-2.1.1.dist-info/WHEEL
freesurfer_volume_reader-2.1.1.dist-info/entry_points.txt
freesurfer_volume_reader-2.1.1.dist-info/top_level.txt
freesurfer_volume_reader-2.1.1.dist-info/RECORD
