Metadata-Version: 2.1
Name: freesurfer-volume-reader
Version: 2.1.1
Summary: Python script & library to read hippocampal subfield volumescomputed by Freesurfer & ASHS
Home-page: https://github.com/fphammerle/freesurfer-volume-reader
Author: Fabian Peter Hammerle
Author-email: fabian@hammerle.me
License: UNKNOWN
Keywords: brain,freesurfer,hippocampus,neuroimaging,reader,subfields
Platform: UNKNOWN
Classifier: Development Status :: 3 - Alpha
Classifier: Intended Audience :: Healthcare Industry
Classifier: Intended Audience :: Science/Research
Classifier: Programming Language :: Python :: 3.5
Classifier: Programming Language :: Python :: 3.6
Classifier: Programming Language :: Python :: 3.7
Classifier: Programming Language :: Python :: 3.8
Classifier: Programming Language :: Python :: 3.9
Classifier: Topic :: Scientific/Engineering :: Information Analysis
Classifier: Topic :: Scientific/Engineering :: Medical Science Apps.
Classifier: Topic :: Utilities
Requires-Dist: pandas (<2,>=0.21.0)
